CHANGES.txt
MANIFEST.in
README.txt
setup.py
RapidGiza.egg-info/PKG-INFO
RapidGiza.egg-info/SOURCES.txt
RapidGiza.egg-info/dependency_links.txt
RapidGiza.egg-info/entry_points.txt
RapidGiza.egg-info/not-zip-safe
RapidGiza.egg-info/requires.txt
RapidGiza.egg-info/top_level.txt
rapidgiza/__init__.py
rapidgiza/paster.py
rapidgiza/paster_template/+project+.wsgi_tmpl
rapidgiza/paster_template/CHANGES.txt_tmpl
rapidgiza/paster_template/MANIFEST.in_tmpl
rapidgiza/paster_template/README.txt_tmpl
rapidgiza/paster_template/development.ini_tmpl
rapidgiza/paster_template/setup.py_tmpl
rapidgiza/paster_template/+package+/__init__.py_tmpl
rapidgiza/paster_template/+package+/main.py_tmpl
rapidgiza/paster_template/+package+/models.py_tmpl
rapidgiza/paster_template/+package+/tests.py_tmpl
rapidgiza/paster_template/+package+/traversal.py_tmpl
rapidgiza/paster_template/+package+/views.py_tmpl
rapidgiza/paster_template/+package+/static/favicon.ico
rapidgiza/paster_template/+package+/static/footerbg.png
rapidgiza/paster_template/+package+/static/headerbg.png
rapidgiza/paster_template/+package+/static/ie6.css
rapidgiza/paster_template/+package+/static/middlebg.png
rapidgiza/paster_template/+package+/static/pylons.css
rapidgiza/paster_template/+package+/static/pyramid-small.png
rapidgiza/paster_template/+package+/static/pyramid.png
rapidgiza/paster_template/+package+/static/transparent.gif
rapidgiza/paster_template/+package+/templates/layout.jinja2
rapidgiza/paster_template/+package+/templates/main.jinja2