Metadata-Version: 1.0
Name: RapidGiza
Version: 0.2.1
Summary: Set of paster templates for rapid Pyramid development
Home-page: https://github.com/serverzen/RapidGiza
Author: Rocky Burt
Author-email: rocky@serverzen.com
License: UNKNOWN
Keywords: web wsgi bfg pylons pyramid sqlalchemy khufu jinja2
Platform: UNKNOWN
Classifier: Intended Audience :: Developers
Classifier: Programming Language :: Python
Classifier: Topic :: Internet :: WWW/HTTP
Classifier: Topic :: Internet :: WWW/HTTP :: Dynamic Content
Classifier: Topic :: Internet :: WWW/HTTP :: WSGI
Classifier: Topic :: Internet :: WWW/HTTP :: WSGI :: Application
